oihelper/__init__.py
oihelper/__main__.py
oihelper/auth.py
oihelper/common.py
oihelper/judger.py
oihelper/parser.py
oihelper/submitter.py
oihelper/cli/__init__.py
oihelper/cli/common.py
oihelper/cli/login.py
oihelper/cli/parse_problem.py
oihelper/cli/run_program.py
oihelper/cli/submit_program.py
oihelper-0.2.3.dist-info/LICENSE
oihelper-0.2.3.dist-info/METADATA
oihelper-0.2.3.dist-info/WHEEL
oihelper-0.2.3.dist-info/entry_points.txt
oihelper-0.2.3.dist-info/top_level.txt
oihelper-0.2.3.dist-info/RECORD
