Metadata-Version: 2.1
Name: oihelper
Version: 0.2.3
Summary: Yet another helper for Olympiad in Informatics.
Author-email: Sam Zhang <samzhangjy@outlook.com>
License: Copyright 2022 Sam Zhang        
Project-URL: Homepage, https://github.com/samzhangjy/oi-helper
Keywords: helper,cli,oi,click
Classifier: License :: OSI Approved :: MIT License
Classifier: Programming Language :: Python
Classifier: Programming Language :: Python :: 3
Requires-Python: >=3.10
License-File: LICENSE
Requires-Dist: click (>=8.1.3)
Requires-Dist: requests (>=2.28.1)
Requires-Dist: psutil (>=5.9.1)
Provides-Extra: dev
Requires-Dist: black ; extra == 'dev'
Requires-Dist: pip-tools ; extra == 'dev'
Requires-Dist: bumpver ; extra == 'dev'
